GPT4Readability/__init__.py
GPT4Readability/__main__.py
GPT4Readability/readme_gen.py
GPT4Readability/suggestions_gen.py
GPT4Readability/utils.py
GPT4Readability/prompts/__init__.py
GPT4Readability/prompts/readme_prompt.txt
GPT4Readability/prompts/readme_prompt_open.txt
GPT4Readability/prompts/refactor_prompt.txt
GPT4Readability-0.1.5.dist-info/LICENSE
GPT4Readability-0.1.5.dist-info/METADATA
GPT4Readability-0.1.5.dist-info/WHEEL
GPT4Readability-0.1.5.dist-info/entry_points.txt
GPT4Readability-0.1.5.dist-info/top_level.txt
GPT4Readability-0.1.5.dist-info/RECORD
