Metadata-Version: 2.1
Name: GPT4Readability
Version: 0.1.5
Summary: A tool to automatically generate a README.md and suggest code improvements for any code repository.  It uses GPT-3, GPT-4, or an optional LocalAI model to generate the README.md and suggestions.
Home-page: https://github.com/loevlie/GPT4Readability
Author: Dennis Johan Loevlie
Author-email: loevliedenny@gmail.com
Classifier: Development Status :: 3 - Alpha
Classifier: Intended Audience :: Developers
Classifier: Topic :: Software Development :: Build Tools
Classifier: Programming Language :: Python :: 3.6
Classifier: Programming Language :: Python :: 3.7
Classifier: Programming Language :: Python :: 3.8
Classifier: Programming Language :: Python :: 3.9
Classifier: Programming Language :: Python :: 3.10
Requires-Python: >=3.6
License-File: LICENSE
Requires-Dist: langchain
Requires-Dist: openai
Requires-Dist: faiss-cpu
Requires-Dist: tiktoken
Requires-Dist: click
Requires-Dist: tqdm
Requires-Dist: unstructured
Requires-Dist: markdown
Requires-Dist: nbconvert
Requires-Dist: typer[all]
Requires-Dist: pyyaml
